

[{"file_name":"Reports.pdf","param1":"","param2":"yh","param3":""}, {"file_name":"Sale Deed.pdf","param1":"","param2":"","param3":""}, {"file_name":"Undertaking.pdf","param1":"","param2":"sdsd","param3":""}, {"file_name":"deed of sale.pdf","param1":"","param2":"","param3":""}, {"file_name":"Receipt.pdf","param1":"","param2":"","param3":""}, {"file_name":"Report 2.pdf","param1":"","param2":"","param3":""}, {"file_name":"460 Deed Of Sale.pdf","param1":"nachinola","param2":"44\/10","param3":""}, {"file_name":"Agreement of Gurudas.pdf","param1":"","param2":"","param3":""}, {"file_name":"Deed of Conveyance.pdf","param1":"","param2":"","param3":""}, {"file_name":"Deed of Sale Maya.pdf","param1":"","param2":"","param3":""}, {"file_name":"Deed of Sale of Goa,Daman & Diu.pdf","param1":"","param2":"","param3":""}, {"file_name":"Deed of Succession.pdf","param1":"","param2":"","param3":""}, {"file_name":"Deed of sale of Devendra.pdf","param1":"","param2":"","param3":""}, {"file_name":"Krishay Report Cards and Certificates.pdf","param1":"nachinol","param2":"33\/10","param3":""}, {"file_name":"Oral Judgment.pdf","param1":"","param2":"hii","param3":""}, {"file_name":"Qlification Certificates of Gopikant.pdf","param1":"","param2":"","param3":""}]
